integration_tests/__init__.py
integration_tests/base_routes.py
integration_tests/conftest.py
integration_tests/index.py
integration_tests/test_add_route_without_decorator.py
integration_tests/test_app.py
integration_tests/test_authentication.py
integration_tests/test_base_url.py
integration_tests/test_basic_routes.py
integration_tests/test_binary_output.py
integration_tests/test_delete_requests.py
integration_tests/test_dependency_injection.py
integration_tests/test_exception_handling.py
integration_tests/test_file_download.py
integration_tests/test_get_requests.py
integration_tests/test_middlewares.py
integration_tests/test_multipart_data.py
integration_tests/test_openapi.py
integration_tests/test_patch_requests.py
integration_tests/test_post_requests.py
integration_tests/test_put_requests.py
integration_tests/test_request_json.py
integration_tests/test_split_request_params.py
integration_tests/test_sse.py
integration_tests/test_status_code.py
integration_tests/test_subrouter.py
integration_tests/test_web_sockets.py
integration_tests/helpers/__init__.py
integration_tests/helpers/http_methods_helpers.py
integration_tests/helpers/network_helpers.py
integration_tests/subroutes/__init__.py
integration_tests/subroutes/di_subrouter.py
mseep_robyn-0.71.1.dist-info/licenses/LICENSE
robyn/__init__.py
robyn/__main__.py
robyn/ai.py
robyn/argument_parser.py
robyn/authentication.py
robyn/cli.py
robyn/dependency_injection.py
robyn/env_populator.py
robyn/events.py
robyn/exceptions.py
robyn/jsonify.py
robyn/logger.py
robyn/mcp.py
robyn/openapi.py
robyn/processpool.py
robyn/py.typed
robyn/reloader.py
robyn/responses.py
robyn/robyn.pyi
robyn/router.py
robyn/status_codes.py
robyn/templating.py
robyn/types.py
robyn/ws.py
mseep_robyn-0.71.1.dist-info/METADATA
mseep_robyn-0.71.1.dist-info/WHEEL
mseep_robyn-0.71.1.dist-info/top_level.txt
mseep_robyn-0.71.1.dist-info/RECORD
